forgefrenzy/__init__.py
forgefrenzy/__main__.py
forgefrenzy/db.py
forgefrenzy/df.sqlite
forgefrenzy/exceptions.py
forgefrenzy/pieces.py
forgefrenzy/products.py
forgefrenzy/store.py
forgefrenzy/version.py
forgefrenzy/blueplate/__init__.py
forgefrenzy/blueplate/defaults.toml
forgefrenzy/blueplate/imports.py
forgefrenzy/blueplate/logger.py
forgefrenzy/blueplate/special.py
forgefrenzy/blueplate/version.py
forgefrenzy-0.1.24.dist-info/LICENSE
forgefrenzy-0.1.24.dist-info/METADATA
forgefrenzy-0.1.24.dist-info/WHEEL
forgefrenzy-0.1.24.dist-info/top_level.txt
forgefrenzy-0.1.24.dist-info/RECORD
