Metadata-Version: 2.1
Name: forgefrenzy
Version: 0.1.24
Summary: A collection of tools to nurture your addiction to Dwarven Forge
Home-page: https://github.com/lawnmowerlatte/forgefrenzy
Author: lawnmowerlatte
Author-email: lawnmowerlatte@gmail.com
Project-URL: Bug Tracker, https://github.com/lawnmowerlatte/forgefrenzy/issues
Classifier: Programming Language :: Python :: 3
Classifier: License :: OSI Approved :: MIT License
Classifier: Operating System :: OS Independent
Requires-Python: >=3.10
License-File: LICENSE
Requires-Dist: minimock
Requires-Dist: requests
Requires-Dist: selenium
Requires-Dist: sqlalchemy
Requires-Dist: beautifulsoup4
Requires-Dist: tomli (>=1.1.0) ; python_version < "3.11"
Provides-Extra: dev
Requires-Dist: black ; extra == 'dev'
Requires-Dist: build ; extra == 'dev'
Requires-Dist: minimock ; extra == 'dev'
Requires-Dist: semver ; extra == 'dev'
Requires-Dist: twine ; extra == 'dev'
